[
  {
    "uid": 0,
    "name": "Debug Block",
    "doSerialization": true,
    "isDead": false,
    "components": [
      {
        "type": "components.Transform",
        "properties": {
          "position": {
            "x": 0.0,
            "y": 0.0,
            "z": 0.0
          },
          "scale": {
            "x": 0.8,
            "y": 0.8
          },
          "rotation": 0.0,
          "uid": 0
        }
      },
      {
        "type": "components.SpriteRenderer",
        "properties": {
          "color": {
            "x": 1.0,
            "y": 1.0,
            "z": 1.0,
            "w": 1.0
          },
          "isDirty": true,
          "sprite": {
            "texture": {
              "filepath": "app/assets/sprites/terrain/ground/Dungeon_floor_sprites.png",
              "width": 96,
              "height": 160
            },
            "width": 16,
            "height": 16,
            "x": 32,
            "y": 144
          },
          "uid": 1
        }
      },
      {
        "type": "components.DebugTimer",
        "properties": {
          "timer": 300,
          "maxTime": 300,
          "uid": 2
        }
      }
    ]
  },
  {
    "uid": 1,
    "name": "Debug Block",
    "doSerialization": true,
    "isDead": false,
    "components": [
      {
        "type": "components.Transform",
        "properties": {
          "position": {
            "x": 16.0,
            "y": 0.0,
            "z": 0.0
          },
          "scale": {
            "x": 0.8,
            "y": 0.8
          },
          "rotation": 0.0,
          "uid": 3
        }
      },
      {
        "type": "components.SpriteRenderer",
        "properties": {
          "color": {
            "x": 1.0,
            "y": 1.0,
            "z": 1.0,
            "w": 1.0
          },
          "isDirty": true,
          "sprite": {
            "texture": {
              "filepath": "app/assets/sprites/terrain/ground/Dungeon_floor_sprites.png",
              "width": 96,
              "height": 160
            },
            "width": 16,
            "height": 16,
            "x": 48,
            "y": 144
          },
          "uid": 4
        }
      }
    ]
  },
  {
    "uid": 2,
    "name": "Debug Block",
    "doSerialization": true,
    "isDead": false,
    "components": [
      {
        "type": "components.Transform",
        "properties": {
          "position": {
            "x": 32.0,
            "y": 0.0,
            "z": 0.0
          },
          "scale": {
            "x": 0.8,
            "y": 0.8
          },
          "rotation": 0.0,
          "uid": 5
        }
      },
      {
        "type": "components.SpriteRenderer",
        "properties": {
          "color": {
            "x": 1.0,
            "y": 1.0,
            "z": 1.0,
            "w": 1.0
          },
          "isDirty": true,
          "sprite": {
            "texture": {
              "filepath": "app/assets/sprites/terrain/ground/Dungeon_floor_sprites.png",
              "width": 96,
              "height": 160
            },
            "width": 16,
            "height": 16,
            "x": 0,
            "y": 0
          },
          "uid": 6
        }
      }
    ]
  },
  {
    "uid": 3,
    "name": "Debug Block",
    "doSerialization": true,
    "isDead": false,
    "components": [
      {
        "type": "components.Transform",
        "properties": {
          "position": {
            "x": 48.0,
            "y": 0.0,
            "z": 0.0
          },
          "scale": {
            "x": 0.8,
            "y": 0.8
          },
          "rotation": 0.0,
          "uid": 7
        }
      },
      {
        "type": "components.SpriteRenderer",
        "properties": {
          "color": {
            "x": 1.0,
            "y": 1.0,
            "z": 1.0,
            "w": 1.0
          },
          "isDirty": true,
          "sprite": {
            "texture": {
              "filepath": "app/assets/sprites/terrain/ground/Dungeon_floor_sprites.png",
              "width": 96,
              "height": 160
            },
            "width": 16,
            "height": 16,
            "x": 16,
            "y": 0
          },
          "uid": 8
        }
      }
    ]
  }
]